np_probe_targets-0.0.13.dist-info/METADATA
np_probe_targets-0.0.13.dist-info/WHEEL
np_probe_targets/.mypy_cache/.gitignore
np_probe_targets/.mypy_cache/3.11/@plugins_snapshot.json
np_probe_targets/.mypy_cache/3.11/__future__.data.json
np_probe_targets/.mypy_cache/3.11/__future__.meta.json
np_probe_targets/.mypy_cache/3.11/_ast.data.json
np_probe_targets/.mypy_cache/3.11/_ast.meta.json
np_probe_targets/.mypy_cache/3.11/_codecs.data.json
np_probe_targets/.mypy_cache/3.11/_codecs.meta.json
np_probe_targets/.mypy_cache/3.11/_collections_abc.data.json
np_probe_targets/.mypy_cache/3.11/_collections_abc.meta.json
np_probe_targets/.mypy_cache/3.11/_typeshed/__init__.data.json
np_probe_targets/.mypy_cache/3.11/_typeshed/__init__.meta.json
np_probe_targets/.mypy_cache/3.11/_winapi.data.json
np_probe_targets/.mypy_cache/3.11/_winapi.meta.json
np_probe_targets/.mypy_cache/3.11/abc.data.json
np_probe_targets/.mypy_cache/3.11/abc.meta.json
np_probe_targets/.mypy_cache/3.11/builtins.data.json
np_probe_targets/.mypy_cache/3.11/builtins.meta.json
np_probe_targets/.mypy_cache/3.11/codecs.data.json
np_probe_targets/.mypy_cache/3.11/codecs.meta.json
np_probe_targets/.mypy_cache/3.11/collections/__init__.data.json
np_probe_targets/.mypy_cache/3.11/collections/__init__.meta.json
np_probe_targets/.mypy_cache/3.11/collections/abc.data.json
np_probe_targets/.mypy_cache/3.11/collections/abc.meta.json
np_probe_targets/.mypy_cache/3.11/contextlib.data.json
np_probe_targets/.mypy_cache/3.11/contextlib.meta.json
np_probe_targets/.mypy_cache/3.11/dataclasses.data.json
np_probe_targets/.mypy_cache/3.11/dataclasses.meta.json
np_probe_targets/.mypy_cache/3.11/datetime.data.json
np_probe_targets/.mypy_cache/3.11/datetime.meta.json
np_probe_targets/.mypy_cache/3.11/email/__init__.data.json
np_probe_targets/.mypy_cache/3.11/email/__init__.meta.json
np_probe_targets/.mypy_cache/3.11/email/charset.data.json
np_probe_targets/.mypy_cache/3.11/email/charset.meta.json
np_probe_targets/.mypy_cache/3.11/email/contentmanager.data.json
np_probe_targets-0.0.13.dist-info/RECORD
