Metadata-Version: 2.1
Name: np_probe_targets
Version: 0.0.13
Summary: Tools for Neuropixels probe insertion: providing suggested targets, recording actual insertions, storing notes.
Author-Email: bjhardcastle <ben.hardcastle@alleninstitute.org>
License: MIT
Classifier: Programming Language :: Python :: 3
Classifier: Programming Language :: Python :: 3.8
Classifier: Programming Language :: Python :: 3.9
Classifier: Programming Language :: Python :: 3.10
Classifier: Programming Language :: Python :: 3.11
Classifier: License :: OSI Approved :: MIT License
Classifier: Operating System :: Microsoft :: Windows
Classifier: Operating System :: POSIX :: Linux
Project-URL: Repository, https://github.com/AllenInstitute/np_probe_targets
Project-URL: Issues, https://github.com/AllenInstitute/np_probe_targets/issues
Requires-Python: >=3.8
Requires-Dist: ipywidgets>=7
Requires-Dist: bump>=1.3.2; extra == "dev"
Provides-Extra: dev
